pulumi_gitlab/__init__.py
pulumi_gitlab/_inputs.py
pulumi_gitlab/_utilities.py
pulumi_gitlab/application.py
pulumi_gitlab/application_appearance.py
pulumi_gitlab/application_settings.py
pulumi_gitlab/branch.py
pulumi_gitlab/branch_protection.py
pulumi_gitlab/cluster_agent.py
pulumi_gitlab/cluster_agent_token.py
pulumi_gitlab/compliance_framework.py
pulumi_gitlab/deploy_key.py
pulumi_gitlab/deploy_key_enable.py
pulumi_gitlab/deploy_token.py
pulumi_gitlab/get_application.py
pulumi_gitlab/get_branch.py
pulumi_gitlab/get_cluster_agent.py
pulumi_gitlab/get_cluster_agents.py
pulumi_gitlab/get_compliance_framework.py
pulumi_gitlab/get_current_user.py
pulumi_gitlab/get_group.py
pulumi_gitlab/get_group_access_tokens.py
pulumi_gitlab/get_group_billable_member_memberships.py
pulumi_gitlab/get_group_hook.py
pulumi_gitlab/get_group_hooks.py
pulumi_gitlab/get_group_ids.py
pulumi_gitlab/get_group_membership.py
pulumi_gitlab/get_group_provisioned_users.py
pulumi_gitlab/get_group_saml_links.py
pulumi_gitlab/get_group_service_account.py
pulumi_gitlab/get_group_subgroups.py
pulumi_gitlab/get_group_variable.py
pulumi_gitlab/get_group_variables.py
pulumi_gitlab/get_groups.py
pulumi_gitlab/get_instance_deploy_keys.py
pulumi_gitlab/get_instance_service_account.py
pulumi_gitlab/get_instance_variable.py
pulumi_gitlab/get_instance_variables.py
pulumi_gitlab/get_metadata.py
pulumi_gitlab/get_pipeline_schedule.py
pulumi_gitlab/get_pipeline_schedules.py
pulumi_gitlab/get_project.py
pulumi_gitlab/get_project_access_tokens.py
pulumi_gitlab/get_project_approval_rules.py
pulumi_gitlab/get_project_branches.py
pulumi_gitlab/get_project_environments.py
pulumi_gitlab/get_project_hook.py
pulumi_gitlab/get_project_hooks.py
pulumi_gitlab/get_project_ids.py
pulumi_gitlab/get_project_issue.py
pulumi_gitlab/get_project_issues.py
pulumi_gitlab/get_project_membership.py
pulumi_gitlab/get_project_merge_request.py
pulumi_gitlab/get_project_merge_requests.py
pulumi_gitlab/get_project_milestone.py
pulumi_gitlab-9.4.0.dist-info/METADATA
pulumi_gitlab-9.4.0.dist-info/WHEEL
pulumi_gitlab-9.4.0.dist-info/top_level.txt
pulumi_gitlab-9.4.0.dist-info/RECORD
